aiauto/__init__.py
aiauto/_config.py
aiauto/constants.py
aiauto/core.py
aiauto/generic_client_interceptor.py
aiauto/grpc_helper.py
aiauto/grpc_storage.py
aiauto/http_client.py
aiauto/path_prefix_interceptor.py
aiauto/serializer.py
aiauto/util.py
aiauto_client-0.2.4.dist-info/METADATA
aiauto_client-0.2.4.dist-info/WHEEL
aiauto_client-0.2.4.dist-info/top_level.txt
aiauto_client-0.2.4.dist-info/RECORD
