Metadata-Version: 2.1
Name: aiauto-client
Version: 0.2.4
Summary: AI Auto HPO (Hyperparameter Optimization) Client Library
Author-email: AIAuto Team <ainode@zeroone.ai>
Project-URL: Homepage, https://dashboard.common.aiauto.pangyo.ainode.ai
Project-URL: Repository, https://dashboard.common.aiauto.pangyo.ainode.ai
Project-URL: Documentation, https://dashboard.common.aiauto.pangyo.ainode.ai
Classifier: Development Status :: 3 - Alpha
Classifier: Intended Audience :: Developers
Classifier: Intended Audience :: Science/Research
Classifier: Programming Language :: Python :: 3
Classifier: Programming Language :: Python :: 3.8
Classifier: Programming Language :: Python :: 3.9
Classifier: Programming Language :: Python :: 3.10
Classifier: Programming Language :: Python :: 3.11
Classifier: Programming Language :: Python :: 3.12
Classifier: Programming Language :: Python :: 3.13
Classifier: Topic :: Scientific/Engineering :: Artificial Intelligence
Classifier: Topic :: Software Development :: Libraries :: Python Modules
Requires-Python: >=3.8.1
Requires-Dist: optuna>=3.0.0
Requires-Dist: optuna-dashboard>=0.18.0
Requires-Dist: requests>=2.25.0
Requires-Dist: grpcio>=1.48.0
Requires-Dist: grpcio-status>=1.48.0
Requires-Dist: tenacity>=9.0.0
